{
  "users": [
    {
      "email": "admin@ad.ad",
      "password": "f6fdffe48c908deb0f4c3bd36c032e72",
      "name": "d",
      "createdDateUnix": "1515609014.804",
      "id": 1
    },
    {
      "email": "admin@ad.ad",
      "password": "f6fdffe48c908deb0f4c3bd36c032e72",
      "name": "ssdfsf",
      "createdDateUnix": "1515609026.54",
      "id": 2
    },
    {
      "email": "admin@ad.ad",
      "password": "f6fdffe48c908deb0f4c3bd36c032e72",
      "name": "sf",
      "createdDateUnix": "1515609065.547",
      "id": 3
    },
    {
      "email": "admin@ad.ad",
      "password": "f6fdffe48c908deb0f4c3bd36c032e72",
      "name": "dfg",
      "createdDateUnix": "1515609598.525",
      "id": 4
    },
    {
      "email": "admin@ad.ad2",
      "password": "f6fdffe48c908deb0f4c3bd36c032e72",
      "name": "fsdf",
      "createdDateUnix": "1515609663.588",
      "id": 5
    }
  ]
}